drf_roles/__init__.py
drf_roles/mixins.py
drf_roles/tests.py
django_rest_framework_roles-0.6.dist-info/LICENSE
django_rest_framework_roles-0.6.dist-info/METADATA
django_rest_framework_roles-0.6.dist-info/WHEEL
django_rest_framework_roles-0.6.dist-info/top_level.txt
django_rest_framework_roles-0.6.dist-info/RECORD
