Metadata-Version: 2.1
Name: django-rest-framework-roles
Version: 0.6
Summary: Parameterizes Django REST Framework methods over user-defined roles
Home-page: http://computerlab.io/
Author: Robert C Jensen
Author-email: rob@computerlab.io
License: BSD License
Platform: UNKNOWN
Classifier: Development Status :: 3 - Alpha
Classifier: Environment :: Web Environment
Classifier: Framework :: Django
Classifier: Intended Audience :: Developers
Classifier: License :: OSI Approved :: BSD License
Classifier: Operating System :: OS Independent
Classifier: Programming Language :: Python
Classifier: Programming Language :: Python :: 2
Classifier: Programming Language :: Python :: 2.7
Classifier: Topic :: Internet :: WWW/HTTP
Classifier: Topic :: Software Development :: Libraries :: Python Modules
